simplerocks/__init__.py
simplerocks/rocks.py
simplerocks-0.0.9.dist-info/LICENSE
simplerocks-0.0.9.dist-info/METADATA
simplerocks-0.0.9.dist-info/WHEEL
simplerocks-0.0.9.dist-info/top_level.txt
simplerocks-0.0.9.dist-info/RECORD
