Metadata-Version: 2.1
Name: simplerocks
Version: 0.0.9
Summary: A few helper utilities to the dataset pip package
Home-page: https://github.com/kapily/simplerocks
Author: Kapil Yedidi
Author-email: kapily.code@gmail.com
License: UNKNOWN
Platform: UNKNOWN
Classifier: Programming Language :: Python :: 3
Classifier: License :: OSI Approved :: MIT License
Classifier: Operating System :: OS Independent
Requires-Python: >=3.0
Requires-Dist: python-rocksdb (==0.*,>=0.7.0)
